bluevision/.DS_Store
bluevision/__about__.py
bluevision/__init__.py
bluevision/demo/__init__.py
bluevision/solutions/__init__.py
bluevision/solutions/detector/README.md
bluevision/solutions/detector/__init__.py
bluevision/solutions/detector/models/__init__.py
bluevision/solutions/detector/models/yolov8.py
bluevision/utils/__init__.py
bluevision/utils/general.py
bluevision/utils/nms/README.md
bluevision/utils/nms/__init__.py
bluevision/utils/tracker/__init__.py
bluevision/utils/tracker/bytetrack/__init__.py
bluevision/utils/tracker/bytetrack/basetrack.py
bluevision/utils/tracker/bytetrack/byte_tracker.py
bluevision/utils/tracker/bytetrack/kalman_filter.py
bluevision/utils/tracker/bytetrack/matching.py
bluevision-0.0.6.dist-info/METADATA
bluevision-0.0.6.dist-info/WHEEL
bluevision-0.0.6.dist-info/licenses/LICENSE.txt
bluevision-0.0.6.dist-info/RECORD
