Metadata-Version: 2.1
Name: bluevision
Version: 0.0.6
Summary: Bluesignal Vision AI project
Project-URL: Documentation, https://github.com/dh031200/bluevision#readme
Project-URL: Issues, https://github.com/dh031200/bluevision/issues
Project-URL: Source, https://github.com/dh031200/bluevision
Author-email: dh031200 <imbird0312@gmail.com>
License-Expression: MIT
License-File: LICENSE.txt
Keywords: AI,Bluesignal,computer-vision
Classifier: Development Status :: 4 - Beta
Classifier: Programming Language :: Python
Classifier: Programming Language :: Python :: 3.8
Classifier: Programming Language :: Python :: 3.9
Classifier: Programming Language :: Python :: 3.10
Classifier: Programming Language :: Python :: 3.11
Classifier: Programming Language :: Python :: 3.12
Classifier: Programming Language :: Python :: Implementation :: CPython
Requires-Python: >=3.8
Requires-Dist: lapx>=0.5.2
Requires-Dist: loguru
Requires-Dist: numpy
Requires-Dist: opencv-python
Requires-Dist: safetensors
Requires-Dist: scipy
Requires-Dist: supervision
Requires-Dist: torch
Requires-Dist: torchvision
